adafruit_miniesptool.py
adafruit_circuitpython_miniesptool-0.2.25.dist-info/licenses/LICENSE
adafruit_circuitpython_miniesptool-0.2.25.dist-info/METADATA
adafruit_circuitpython_miniesptool-0.2.25.dist-info/WHEEL
adafruit_circuitpython_miniesptool-0.2.25.dist-info/top_level.txt
adafruit_circuitpython_miniesptool-0.2.25.dist-info/RECORD
