Metadata-Version: 2.4
Name: adafruit-circuitpython-miniesptool
Version: 0.2.25
Summary: CircuitPython ROM loader for ESP chips, works with ESP8266 or ESP32.
Author-email: Adafruit Industries <circuitpython@adafruit.com>
License: MIT
Project-URL: Homepage, https://github.com/adafruit/Adafruit_CircuitPython_miniesptool
Keywords: adafruit,miniesptool,esp8266,esp32,esp,software,micropython,circuitpython
Classifier: Intended Audience :: Developers
Classifier: Topic :: Software Development :: Libraries
Classifier: Topic :: Software Development :: Embedded Systems
Classifier: Topic :: System :: Hardware
Classifier: License :: OSI Approved :: MIT License
Classifier: Programming Language :: Python :: 3
License-File: LICENSE
Requires-Dist: Adafruit-Blinka
Requires-Dist: pyserial
Provides-Extra: optional
Dynamic: license-file
